{
  "name": "The rat I am looking at",
  "sex": "X",
  "id": "INC00001M",
  "_parents": [
    {
      "name": "Mother",
      "sex": "F",
      "id": "INC00002F",
      "_parents": [
        {
          "name": "Maternal Grandmother",
          "sex": "F",
          "id": "INC00004F"
        },
        {
          "name": "Maternal Grandfather",
          "sex": "M",
          "id": "INC00005M"
        }
      ]
    },
    {
      "name": "Father",
      "sex": "M",
      "id": "INC00003M",
      "_parents": [
        {
          "name": "Paternal Grandmother",
          "sex": "F",
          "id": "INC00006F"
        },
        {
          "name": "Paternal Grandfather",
          "sex": "M",
          "id": "INC00007M"
        }
      ]
    }
  ],
  "_children": [
  ]
}
